[
    {
      "TownCode": "6800200",
      "TownName": "中壢區"
    },
    {
      "TownCode": "6801000",
      "TownName": "平鎮區"
    },
    {
      "TownCode": "6800900",
      "TownName": "龍潭區"
    },
    {
      "TownCode": "6800400",
      "TownName": "楊梅區"
    },
    {
      "TownCode": "6801100",
      "TownName": "新屋區"
    },
    {
      "TownCode": "6801200",
      "TownName": "觀音區"
    },
    {
      "TownCode": "6800100",
      "TownName": "桃園區"
    },
    {
      "TownCode": "6800700",
      "TownName": "龜山區"
    },
    {
      "TownCode": "6800800",
      "TownName": "八德區"
    },
    {
      "TownCode": "6800300",
      "TownName": "大溪區"
    },
    {
      "TownCode": "6801300",
      "TownName": "復興區"
    },
    {
      "TownCode": "6800600",
      "TownName": "大園區"
    },
    {
      "TownCode": "6800500",
      "TownName": "蘆竹區"
    }
  ]